lala/WebLogs.py
lala/__init__.py
lala/conf.py
lala/version.py
python_lala-0.1.4.dist-info/LICENCE.txt
python_lala-0.1.4.dist-info/METADATA
python_lala-0.1.4.dist-info/WHEEL
python_lala-0.1.4.dist-info/top_level.txt
python_lala-0.1.4.dist-info/RECORD
