Metadata-Version: 2.1
Name: python-lala
Version: 0.1.4
Summary: Library of web access log analysis
Home-page: UNKNOWN
Author: Zulko
License: MIT
Keywords: access log analysis website webservice stats
Platform: UNKNOWN
Requires-Dist: appdirs
Requires-Dist: numpy
Requires-Dist: matplotlib
Requires-Dist: Pillow
Requires-Dist: pygeoip
Requires-Dist: pandas
Requires-Dist: scipy
Requires-Dist: proglog
Requires-Dist: pdf-reports
